h5cli/VERSION
h5cli/__init__.py
h5cli/cli.py
h5cli/explorer.py
h5cli-0.1.0.dist-info/DESCRIPTION.rst
h5cli-0.1.0.dist-info/LICENSE.txt
h5cli-0.1.0.dist-info/METADATA
h5cli-0.1.0.dist-info/RECORD
h5cli-0.1.0.dist-info/WHEEL
h5cli-0.1.0.dist-info/entry_points.txt
h5cli-0.1.0.dist-info/metadata.json
h5cli-0.1.0.dist-info/top_level.txt
